fabrique_nodes_core/__init__.py
fabrique_nodes_core/config.py
fabrique_nodes_core/configs_model.py
fabrique_nodes_core/convertors.py
fabrique_nodes_core/core.py
fabrique_nodes_core/crypto.py
fabrique_nodes_core/jspath_parser.py
fabrique_nodes_core/model_generators.py
fabrique_nodes_core/port_types.py
fabrique_nodes_core/ui_params.py
fabrique_nodes_core/validators.py
fabrique_nodes_core/db/__init__.py
fabrique_nodes_core/db/data_model.py
fabrique_nodes_core/db/fake_db.py
fabrique_nodes_core/db/pg_orm.py
fabrique_nodes_core/stateful/__init__.py
fabrique_nodes_core/stateful/state.py
tests/__init__.py
tests/import_spoofer.py
tests/nodes_for_tests.py
tests/test_0_positive_core.py
tests/test_1_core_validators.py
tests/test_2_positive_convertors.py
tests/test_3_positive_config_model copy.py
tests/test_4_stateful.py
tests/test_5_crypto.py
tests/test_6_proj_db.py
tests/test_7_blocked_db.py
fabrique_nodes_core-0.13.1.dist-info/METADATA
fabrique_nodes_core-0.13.1.dist-info/WHEEL
fabrique_nodes_core-0.13.1.dist-info/top_level.txt
fabrique_nodes_core-0.13.1.dist-info/RECORD
