Metadata-Version: 2.1
Name: fabrique-nodes-core
Version: 0.13.1
Summary: Fabrique nodes SDK
Home-page: http://www.fabrique.ai
Author: Sergey Kuzmin
Author-email: sergey.kuzmin@fabrique.ai
License: MIT
Classifier: Development Status :: 5 - Production/Stable
Classifier: License :: OSI Approved :: MIT License
Requires-Dist: datamodel-code-generator[http] (==0.13.1)
Requires-Dist: cryptography (==41.0.1)
Requires-Dist: pydantic
Requires-Dist: psycopg2-binary (==2.9.6)
Requires-Dist: confluent-kafka (==2.2.0)
Requires-Dist: jmespath (==1.0.1)
